{
  "demo-api/demo-api.raml": "RAML 1.0",
  "array-body/array-body.raml": "RAML 1.0",
  "appian-api/appian-api.raml":  "RAML 1.0",
  "nexmo-sms-api/nexmo-sms-api.raml":  "RAML 1.0",
  "loan-microservice/loan-microservice.json": "OAS 2.0",
  "google-drive-api/google-drive-api.raml": "RAML 1.0",
  "SE-12957/SE-12957.json": "OAS 2.0",
  "SE-12959/SE-12959.json": "OAS 2.0",
  "SE-12752/SE-12752.raml": "RAML 1.0",
  "oas-callbacks/oas-callbacks.yaml": { "type": "OAS 3.0", "mime": "application/yaml" },
  "multi-server/multi-server.yaml": { "type": "OAS 3.0", "mime": "application/yaml" },
  "async-api/async-api.yaml": "ASYNC 2.0",
  "APIC-553/APIC-553.raml": "RAML 1.0",
  "APIC-560/APIC-560.yaml": "ASYNC 2.0"
}
